{"name":"Lectures","allTables":[{"type":"table","tableRows":[{"text":"Section Posts Last Post "},{"text":" Week 5 3 i Tuesday 16 October 2018, 09:21:12 AM "},{"text":" Week 7 3 i Monday 10 September 2018, 01:38:55 PM "},{"text":" Week 3 5 i Tuesday 21 August 2018, 11:17:50 PM "},{"text":" Week 2 2 i Friday 03 August 2018, 10:11:22 AM "},{"text":" Miscellaneous 2 i Monday 23 July 2018, 04:37:38 PM "},{"text":" Week 1 0 Never "},{"text":" Week 4 0 Never "},{"text":" Week 6 0 Never "},{"text":" Week 8 0 Never "},{"text":" Week 9 0 Never "},{"text":" Week 10 0 Never "}]}],"allParagraphs":[{"type":"paragraph"}," Toggle Menu ",{"type":"paragraph"},"Back to top "]}