{"grouped":[{"tags":[{"name":"table","salience":0.5,"theta":1}],"items":[{"tags":[],"text":"networks"}]},{"tags":[{"name":"table","salience":0.5,"theta":1}],"items":[{"tags":[],"text":"networks 2 52"}]},{"tags":[{"name":"table","salience":0.5,"theta":1}],"items":[{"tags":[],"text":"networks 3 52"}]},{"tags":[{"name":"table","salience":0.5,"theta":1}],"items":[{"tags":[],"text":"overview of network communication 4 52"}]},{"tags":[{"name":"table","salience":0.5,"theta":1}],"items":[{"tags":[],"text":"the internet 5 52"}]},{"tags":[{"name":"table","salience":0.5,"theta":1}],"items":[{"tags":[],"text":"components of the internet millions of connected devices e g pc server laptop smartphone host end system running network apps communication links e g fibre copper radio satellite bandwidth transmission rate packet switches e g routers network switches compute next hop forward packets"}]},{"tags":[{"name":"table","salience":0.5,"theta":1}],"items":[{"tags":[],"text":"the internet 6 52"}]},{"tags":[{"name":"table","salience":0.5,"theta":1}],"items":[{"tags":[],"text":"the internet 7 52"}]},{"tags":[{"name":"table","salience":0.5,"theta":1}],"items":[{"tags":[],"text":"protocols 8 52"}]},{"tags":[{"name":"table","salience":0.5,"theta":1}],"items":[{"tags":[],"text":"network application layer 9 52"}]},{"tags":[{"name":"table","salience":0.5,"theta":1}],"items":[{"tags":[],"text":"client server architecture 10 52"}]},{"tags":[{"name":"table","salience":0.5,"theta":1}],"items":[{"tags":[],"text":"addressing 11 52"}]},{"tags":[{"name":"table","salience":0.5,"theta":1}],"items":[{"tags":[],"text":"ip addresses 12 52"}]},{"tags":[{"name":"table","salience":0.5,"theta":1}],"items":[{"tags":[],"text":"application layer protocols 13 52"}]},{"tags":[{"name":"table","salience":0.5,"theta":1}],"items":[{"tags":[],"text":"the http protocol 14 52"}]},{"tags":[{"name":"table","salience":0.5,"theta":1}],"items":[{"tags":[],"text":"the http protocol 15 52"}]},{"tags":[{"name":"table","salience":0.5,"theta":1}],"items":[{"tags":[],"text":"application layer protocol for the web client server model client web browser e g chrome sends http requests receives http responses shows response as web page server web server e g apache receives http requests sends http responses"}]},{"tags":[{"name":"table","salience":0.5,"theta":1}],"items":[{"tags":[],"text":"the http protocol 16 52"}]},{"tags":[{"name":"table","salience":0.5,"theta":1}],"items":[{"tags":[],"text":"the http protocol 17 52"}]},{"tags":[{"name":"table","salience":0.5,"theta":1}],"items":[{"tags":[],"text":"the http protocol 18 52"}]},{"tags":[{"name":"table","salience":0.5,"theta":1}],"items":[{"tags":[],"text":"the http protocol 19 52"}]},{"tags":[{"name":"table","salience":0.5,"theta":1}],"items":[{"tags":[],"text":"the http protocol 20 52"}]},{"tags":[{"name":"table","salience":0.5,"theta":1}],"items":[{"tags":[],"text":"server addresses dns 21 52"}]},{"tags":[{"name":"table","salience":0.5,"theta":1}],"items":[{"tags":[],"text":"server addresses dns 22 52"}]},{"tags":[{"name":"table","salience":0.5,"theta":1}],"items":[{"tags":[],"text":"server addresses dns 23 52"}]},{"tags":[{"name":"table","salience":0.5,"theta":1}],"items":[{"tags":[],"text":"server addresses dns 24 52"}]},{"tags":[{"name":"table","salience":0.5,"theta":1}],"items":[{"tags":[],"text":"server addresses dns 25 52"}]},{"tags":[{"name":"table","salience":0.5,"theta":1}],"items":[{"tags":[],"text":"server addresses dns 26 52"}]},{"tags":[{"name":"table","salience":0.5,"theta":1}],"items":[{"tags":[],"text":"network architecture 27 52"}]},{"tags":[{"name":"table","salience":0.5,"theta":1}],"items":[{"tags":[],"text":"transport layer 28 52"}]},{"tags":[{"name":"table","salience":0.5,"theta":1}],"items":[{"tags":[],"text":"transport layer 29 52"}]},{"tags":[{"name":"table","salience":0.5,"theta":1}],"items":[{"tags":[],"text":"transport layer protocols 30 52"}]},{"tags":[{"name":"table","salience":0.5,"theta":1}],"items":[{"tags":[],"text":"transport layer protocols 31 52"}]},{"tags":[{"name":"table","salience":0.5,"theta":1}],"items":[{"tags":[],"text":"transport layer protocols 32 52"}]},{"tags":[{"name":"table","salience":0.5,"theta":1}],"items":[{"tags":[],"text":"transport layer protocols 33 52"}]},{"tags":[{"name":"table","salience":0.5,"theta":1}],"items":[{"tags":[],"text":"network layer 34 52"}]},{"tags":[{"name":"table","salience":0.5,"theta":1}],"items":[{"tags":[],"text":"network layer protocol 35 52"}]},{"tags":[{"name":"table","salience":0.5,"theta":1}],"items":[{"tags":[],"text":"network layer protocol 36 52"}]},{"tags":[{"name":"table","salience":0.5,"theta":1}],"items":[{"tags":[],"text":"link layer 37 52"}]},{"tags":[{"name":"table","salience":0.5,"theta":1}],"items":[{"tags":[],"text":"ethernet 38 52"}]},{"tags":[{"name":"table","salience":0.5,"theta":1}],"items":[{"tags":[],"text":"ethernet 39 52"}]},{"tags":[{"name":"table","salience":0.5,"theta":1}],"items":[{"tags":[],"text":"ethernet 40 52"}]},{"tags":[{"name":"table","salience":0.5,"theta":1}],"items":[{"tags":[],"text":"wireless sensor network security 41 52"}]},{"tags":[{"name":"table","salience":0.5,"theta":1}],"items":[{"tags":[],"text":"wireless sensor network security 42 52"}]},{"tags":[{"name":"table","salience":0.5,"theta":1}],"items":[{"tags":[],"text":"wireless sensor network security 43 52"}]},{"tags":[{"name":"table","salience":0.5,"theta":1}],"items":[{"tags":[],"text":"wireless sensor network security 44 52"}]},{"tags":[{"name":"table","salience":0.5,"theta":1}],"items":[{"tags":[],"text":"wireless sensor network security 45 52"}]},{"tags":[{"name":"table","salience":0.5,"theta":1}],"items":[{"tags":[],"text":"wsn attacks 46 52"}]},{"tags":[{"name":"table","salience":0.5,"theta":1}],"items":[{"tags":[],"text":"wsn attacks 47 52"}]},{"tags":[{"name":"table","salience":0.5,"theta":1}],"items":[{"tags":[],"text":"wsn attacks 48 52"}]},{"tags":[{"name":"table","salience":0.5,"theta":1}],"items":[{"tags":[],"text":"wsn attacks 49 52"}]},{"tags":[{"name":"table","salience":0.5,"theta":1}],"items":[{"tags":[],"text":"wsn attacks 50 52"}]},{"tags":[{"name":"table","salience":0.5,"theta":1}],"items":[{"tags":[],"text":"wsn attacks 51 52"}]},{"tags":[{"name":"table","salience":0.5,"theta":1}],"items":[{"tags":[],"text":"wsn attacks 52 52"}]},{"tags":[{"name":"list","salience":0.5,"theta":1}],"items":[{"tags":[],"text":"local area networks within an organisation physical location"},{"tags":[],"text":"wide area networks geographically dispersed wan"},{"tags":[],"text":"internet global set of interconnected wans"}]},{"tags":[{"name":"list","salience":0.5,"theta":1}],"items":[{"tags":[],"text":"previously transfer data send text based emails"},{"tags":[],"text":"nowadays communication communication communication"},{"tags":[],"text":"sharing resources e g printers large storage devices"}]},{"tags":[{"name":"list","salience":0.5,"theta":1}],"items":[{"tags":[],"text":"get data from machine a to machine b"},{"tags":[],"text":"a and b may be separated by 100 s of networks and devices"}]},{"tags":[{"name":"list","salience":0.5,"theta":1}],"items":[{"tags":[],"text":"need a unique address for destination"},{"tags":[],"text":"identify a route first post office"},{"tags":[],"text":"process at intermediate nodes other post offices"},{"tags":[],"text":"follow certain protocols envelopes stamps fees"}]},{"tags":[{"name":"list","salience":0.5,"theta":1}],"items":[]},{"tags":[{"name":"list","salience":0.5,"theta":1}],"items":[{"tags":[],"text":"packets are small fixed size chunks of data with headers"}]},{"tags":[{"name":"list","salience":0.5,"theta":1}],"items":[{"tags":[],"text":"each node decides where to send it next for best route"}]},{"tags":[{"name":"list","salience":0.5,"theta":1}],"items":[{"tags":[],"text":"millions of connected devices e g pc server laptop smartphone host end system running network apps"},{"tags":[],"text":"e g pc server laptop smartphone"},{"tags":[],"text":"host end system running network apps"},{"tags":[],"text":"communication links e g fibre copper radio satellite bandwidth transmission rate"},{"tags":[],"text":"e g fibre copper radio satellite"},{"tags":[],"text":"bandwidth transmission rate"},{"tags":[],"text":"packet switches e g routers network switches compute next hop forward packets"},{"tags":[],"text":"e g routers network switches"},{"tags":[],"text":"compute next hop forward packets"}]},{"tags":[{"name":"list","salience":0.5,"theta":1}],"items":[{"tags":[],"text":"e g pc server laptop smartphone"},{"tags":[],"text":"host end system running network apps"}]},{"tags":[{"name":"list","salience":0.5,"theta":1}],"items":[{"tags":[],"text":"e g fibre copper radio satellite"},{"tags":[],"text":"bandwidth transmission rate"}]},{"tags":[{"name":"list","salience":0.5,"theta":1}],"items":[{"tags":[],"text":"e g routers network switches"},{"tags":[],"text":"compute next hop forward packets"}]},{"tags":[{"name":"list","salience":0.5,"theta":1}],"items":[{"tags":[],"text":"physical layer bits on wires or fibre optics or radio"},{"tags":[],"text":"link layer ethernet mac addressing csma etc"},{"tags":[],"text":"network layer routing protocols ip"},{"tags":[],"text":"transport layer process process data transfer tcp udp"},{"tags":[],"text":"application layer dns http email skype torrents ftp etc"}]},{"tags":[{"name":"list","salience":0.5,"theta":1}],"items":[{"tags":[],"text":"each layer encapsulates one aspect of network transport"},{"tags":[],"text":"provides layered reference model for discussion"},{"tags":[],"text":"modularization eases maintenance updating e g changing implementation of one layer doesn t affect other layers"},{"tags":[],"text":"e g changing implementation of one layer doesn t affect other layers"}]},{"tags":[{"name":"list","salience":0.5,"theta":1}],"items":[{"tags":[],"text":"e g changing implementation of one layer doesn t affect other layers"}]},{"tags":[{"name":"list","salience":0.5,"theta":1}],"items":[{"tags":[],"text":"format and order of messages sent received"},{"tags":[],"text":"actions taken on message transmission receipt"}]},{"tags":[{"name":"list","salience":0.5,"theta":1}],"items":[{"tags":[],"text":"link layer ppp point to point protocol"},{"tags":[],"text":"network layer ip internet protoocol"},{"tags":[],"text":"transport layer tcp transmission control udp user datagram"},{"tags":[],"text":"application layer http ftp ssh pop smtp"}]},{"tags":[{"name":"list","salience":0.5,"theta":1}],"items":[{"tags":[],"text":"e mail"},{"tags":[],"text":"web"},{"tags":[],"text":"text messaging"},{"tags":[],"text":"remote login"},{"tags":[],"text":"p2p file sharing"},{"tags":[],"text":"multi user network games"},{"tags":[],"text":"streaming stored video youtube hulu netflix"},{"tags":[],"text":"voice over ip e g skype"},{"tags":[],"text":"real time video conferencing"},{"tags":[],"text":"social networking"}]},{"tags":[{"name":"list","salience":0.5,"theta":1}],"items":[{"tags":[],"text":"process that waits for requests"},{"tags":[],"text":"always on host with permanent ip address"},{"tags":[],"text":"possibly using data centers multiple cpus for scaling"}]},{"tags":[{"name":"list","salience":0.5,"theta":1}],"items":[{"tags":[],"text":"sends requests to server collects response"},{"tags":[],"text":"may be intermittently connected may have dynamic ip address"},{"tags":[],"text":"does not communicate directly with other clients"}]},{"tags":[{"name":"list","salience":0.5,"theta":1}],"items":[{"tags":[],"text":"part of address is ip address of host machine"},{"tags":[],"text":"other part of address is port number where server listens"}]},{"tags":[{"name":"list","salience":0.5,"theta":1}],"items":[{"tags":[],"text":"address of web server on gaia cs umass edu"}]},{"tags":[{"name":"list","salience":0.5,"theta":1}],"items":[{"tags":[],"text":"22 ssh secure shell"},{"tags":[],"text":"25 smtp simple mail transfer protocol"},{"tags":[],"text":"53 dns domain name system"},{"tags":[],"text":"80 http web server"},{"tags":[],"text":"389 ldap lightweight directory access protocol"},{"tags":[],"text":"443 https web server encrypted"},{"tags":[],"text":"5432 postgresql database server"}]},{"tags":[{"name":"list","salience":0.5,"theta":1}],"items":[{"tags":[],"text":"given as a 32 bit identifier dotted quad e g 129 94 242 20"},{"tags":[],"text":"special case 127 0 0 1 loopback address referring to local host"},{"tags":[],"text":"ip addresses are assigned by sys admin entering into local registry for permanent addresses dynamically by getting a temporary address from dhcp server"},{"tags":[],"text":"sys admin entering into local registry for permanent addresses"},{"tags":[],"text":"dynamically by getting a temporary address from dhcp server"}]},{"tags":[{"name":"list","salience":0.5,"theta":1}],"items":[{"tags":[],"text":"sys admin entering into local registry for permanent addresses"},{"tags":[],"text":"dynamically by getting a temporary address from dhcp server"}]},{"tags":[{"name":"list","salience":0.5,"theta":1}],"items":[{"tags":[],"text":"why internet of things every networked device needs an ip"},{"tags":[],"text":"ipv6 uses 128 bit addresses e g 2001 388 c 4193 129 94 242 20"},{"tags":[],"text":"distinct addresses ipv4 4 109 ipv6 3 1038"}]},{"tags":[{"name":"list","salience":0.5,"theta":1}],"items":[{"tags":[],"text":"types of messages different types of requests and responses"},{"tags":[],"text":"different types of requests and responses"},{"tags":[],"text":"message syntax what fields are in messages how fields are delineated"},{"tags":[],"text":"what fields are in messages how fields are delineated"},{"tags":[],"text":"message semantics meaning of information in fields"},{"tags":[],"text":"meaning of information in fields"},{"tags":[],"text":"processing rules when and how processes respond to messages"},{"tags":[],"text":"when and how processes respond to messages"}]},{"tags":[{"name":"list","salience":0.5,"theta":1}],"items":[{"tags":[],"text":"different types of requests and responses"}]},{"tags":[{"name":"list","salience":0.5,"theta":1}],"items":[{"tags":[],"text":"what fields are in messages how fields are delineated"}]},{"tags":[{"name":"list","salience":0.5,"theta":1}],"items":[{"tags":[],"text":"meaning of information in fields"}]},{"tags":[{"name":"list","salience":0.5,"theta":1}],"items":[{"tags":[],"text":"when and how processes respond to messages"}]},{"tags":[{"name":"list","salience":0.5,"theta":1}],"items":[{"tags":[],"text":"an extremely important protocol drives the web"},{"tags":[],"text":"message types urls requests and web pages responses"},{"tags":[],"text":"message syntax headers data see details later"}]},{"tags":[{"name":"list","salience":0.5,"theta":1}],"items":[{"tags":[],"text":"contain html may contain references to other types of objects"},{"tags":[],"text":"all objects are addressable via a url"}]},{"tags":[{"name":"list","salience":0.5,"theta":1}],"items":[{"tags":[],"text":"client web browser e g chrome sends http requests receives http responses shows response as web page"},{"tags":[],"text":"sends http requests"},{"tags":[],"text":"receives http responses"},{"tags":[],"text":"shows response as web page"},{"tags":[],"text":"server web server e g apache receives http requests sends http responses"},{"tags":[],"text":"receives http requests"},{"tags":[],"text":"sends http responses"}]},{"tags":[{"name":"list","salience":0.5,"theta":1}],"items":[{"tags":[],"text":"sends http requests"},{"tags":[],"text":"receives http responses"},{"tags":[],"text":"shows response as web page"}]},{"tags":[{"name":"list","salience":0.5,"theta":1}],"items":[{"tags":[],"text":"receives http requests"},{"tags":[],"text":"sends http responses"}]},{"tags":[{"name":"list","salience":0.5,"theta":1}],"items":[{"tags":[],"text":"using tcp"},{"tags":[],"text":"client initiates tcp connection socket to server port 80"},{"tags":[],"text":"server accepts tcp connection from client"},{"tags":[],"text":"client sends http request messages e g get"},{"tags":[],"text":"server responds with http messages e g html"},{"tags":[],"text":"interaction completes connection socket closed"}]},{"tags":[{"name":"list","salience":0.5,"theta":1}],"items":[{"tags":[],"text":"no need to mention host since connection already established"},{"tags":[],"text":"get requests data from resource specified by path query string is included in the path"},{"tags":[],"text":"query string is included in the path"},{"tags":[],"text":"post submitd data to be processed by specified resource query string is included in the body"},{"tags":[],"text":"query string is included in the body"},{"tags":[],"text":"head same as get but returns only header no data"}]},{"tags":[{"name":"list","salience":0.5,"theta":1}],"items":[{"tags":[],"text":"query string is included in the path"}]},{"tags":[{"name":"list","salience":0.5,"theta":1}],"items":[{"tags":[],"text":"query string is included in the body"}]},{"tags":[{"name":"list","salience":0.5,"theta":1}],"items":[{"tags":[],"text":"202 ok succesful request"},{"tags":[],"text":"301 moved permanently requested object moved returns new url for client to use in future requests"},{"tags":[],"text":"returns new url for client to use in future requests"},{"tags":[],"text":"400 bad request request cannot be processed possible reasons bad request syntax request size too large"},{"tags":[],"text":"possible reasons bad request syntax request size too large"},{"tags":[],"text":"403 forbidden valid request cannot be processed possible reasons user does not have permission for operation"},{"tags":[],"text":"possible reasons user does not have permission for operation"},{"tags":[],"text":"404 not found path does not exist on server"},{"tags":[],"text":"500 internal server error server cannot complete request possible reasons server side script fails database not accessible"},{"tags":[],"text":"possible reasons server side script fails database not accessible"}]},{"tags":[{"name":"list","salience":0.5,"theta":1}],"items":[{"tags":[],"text":"returns new url for client to use in future requests"}]},{"tags":[{"name":"list","salience":0.5,"theta":1}],"items":[{"tags":[],"text":"possible reasons bad request syntax request size too large"}]},{"tags":[{"name":"list","salience":0.5,"theta":1}],"items":[{"tags":[],"text":"possible reasons user does not have permission for operation"}]},{"tags":[{"name":"list","salience":0.5,"theta":1}],"items":[{"tags":[],"text":"possible reasons server side script fails database not accessible"}]},{"tags":[{"name":"list","salience":0.5,"theta":1}],"items":[{"tags":[],"text":"http www cse unsw edu au cs1521 17s2"}]},{"tags":[{"name":"list","salience":0.5,"theta":1}],"items":[{"tags":[],"text":"a person name ssn tfn passport"}]},{"tags":[{"name":"list","salience":0.5,"theta":1}],"items":[{"tags":[],"text":"one or more symbolic names unique ip address"},{"tags":[],"text":"symbolic www cse unsw edu au ip 129 94 242 51"}]},{"tags":[{"name":"list","salience":0.5,"theta":1}],"items":[{"tags":[],"text":"a given ip address may be reachable via several names"},{"tags":[],"text":"a given name may map to several ips e g for load distribution"}]},{"tags":[{"name":"list","salience":0.5,"theta":1}],"items":[{"tags":[],"text":"effectively a distributed database of name ip mappings"},{"tags":[],"text":"implemented across a hierarchy of name servers"},{"tags":[],"text":"name servers cooperate to resolve names to ip addresses"}]},{"tags":[{"name":"list","salience":0.5,"theta":1}],"items":[{"tags":[],"text":"central point of failure high traffic volume"},{"tags":[],"text":"distant database lag maintenance of very large db"}]},{"tags":[{"name":"list","salience":0.5,"theta":1}],"items":[{"tags":[],"text":"contact a root dns server to find com dns server"},{"tags":[],"text":"contact com dns server to get amazon com dns server"},{"tags":[],"text":"contact amazon com dns server to get ip of their web server"}]},{"tags":[{"name":"list","salience":0.5,"theta":1}],"items":[{"tags":[],"text":"iterated query work done by client client contacts name server x gets response i don t know but ask name server y or gets response here is the ip address client repeats above steps until name resolved"},{"tags":[],"text":"client contacts name server x"},{"tags":[],"text":"gets response i don t know but ask name server y"},{"tags":[],"text":"or gets response here is the ip address"},{"tags":[],"text":"client repeats above steps until name resolved"},{"tags":[],"text":"recursive query work done by name servers client contacts name server x x contacts name server y y contacts z query propagates until name resolved"},{"tags":[],"text":"client contacts name server x"},{"tags":[],"text":"x contacts name server y y contacts z"},{"tags":[],"text":"query propagates until name resolved"}]},{"tags":[{"name":"list","salience":0.5,"theta":1}],"items":[{"tags":[],"text":"client contacts name server x"},{"tags":[],"text":"gets response i don t know but ask name server y"},{"tags":[],"text":"or gets response here is the ip address"},{"tags":[],"text":"client repeats above steps until name resolved"}]},{"tags":[{"name":"list","salience":0.5,"theta":1}],"items":[{"tags":[],"text":"client contacts name server x"},{"tags":[],"text":"x contacts name server y y contacts z"},{"tags":[],"text":"query propagates until name resolved"}]},{"tags":[{"name":"list","salience":0.5,"theta":1}],"items":[{"tags":[],"text":"top level domain tld name servers com org edu and all country level domains e g uk network solutions maintains servers for com ausregistry maintains servers for au"},{"tags":[],"text":"com org edu and all country level domains e g uk"},{"tags":[],"text":"network solutions maintains servers for com"},{"tags":[],"text":"ausregistry maintains servers for au"},{"tags":[],"text":"authoritative name servers maintains mappings from names to ip within an organisation all hosts within the organisation are registered here"},{"tags":[],"text":"maintains mappings from names to ip within an organisation"},{"tags":[],"text":"all hosts within the organisation are registered here"},{"tags":[],"text":"local default name servers maintains cache of name ip mappings starting point for dns queries forward to tld server if cached"},{"tags":[],"text":"maintains cache of name ip mappings"},{"tags":[],"text":"starting point for dns queries forward to tld server if cached"}]},{"tags":[{"name":"list","salience":0.5,"theta":1}],"items":[{"tags":[],"text":"com org edu and all country level domains e g uk"},{"tags":[],"text":"network solutions maintains servers for com"},{"tags":[],"text":"ausregistry maintains servers for au"}]},{"tags":[{"name":"list","salience":0.5,"theta":1}],"items":[{"tags":[],"text":"maintains mappings from names to ip within an organisation"},{"tags":[],"text":"all hosts within the organisation are registered here"}]},{"tags":[{"name":"list","salience":0.5,"theta":1}],"items":[{"tags":[],"text":"maintains cache of name ip mappings"},{"tags":[],"text":"starting point for dns queries forward to tld server if cached"}]},{"tags":[{"name":"list","salience":0.5,"theta":1}],"items":[{"tags":[],"text":"lowest least abstract level"},{"tags":[],"text":"physical layer bits on wires"},{"tags":[],"text":"link layer e g ethernet mac"},{"tags":[],"text":"network layer e g ip"},{"tags":[],"text":"transport layer e g tcp udp"},{"tags":[],"text":"application layer e g http email"},{"tags":[],"text":"highest most abstract level"}]},{"tags":[{"name":"list","salience":0.5,"theta":1}],"items":[{"tags":[],"text":"data integrity some apps e g file transfer require 100 reliable transfer other apps e g audio streaming can tolerate some loss"},{"tags":[],"text":"some apps e g file transfer require 100 reliable transfer"},{"tags":[],"text":"other apps e g audio streaming can tolerate some loss"},{"tags":[],"text":"timing some apps e g networked games require low transmission delay"},{"tags":[],"text":"some apps e g networked games require low transmission delay"},{"tags":[],"text":"throughput some apps e g multimedia require minimum throughput other apps elastic apps can use whatever is available"},{"tags":[],"text":"some apps e g multimedia require minimum throughput"},{"tags":[],"text":"other apps elastic apps can use whatever is available"},{"tags":[],"text":"security some apps e g web services require encrypted transmission"},{"tags":[],"text":"some apps e g web services require encrypted transmission"}]},{"tags":[{"name":"list","salience":0.5,"theta":1}],"items":[{"tags":[],"text":"some apps e g file transfer require 100 reliable transfer"},{"tags":[],"text":"other apps e g audio streaming can tolerate some loss"}]},{"tags":[{"name":"list","salience":0.5,"theta":1}],"items":[{"tags":[],"text":"some apps e g networked games require low transmission delay"}]},{"tags":[{"name":"list","salience":0.5,"theta":1}],"items":[{"tags":[],"text":"some apps e g multimedia require minimum throughput"},{"tags":[],"text":"other apps elastic apps can use whatever is available"}]},{"tags":[{"name":"list","salience":0.5,"theta":1}],"items":[{"tags":[],"text":"some apps e g web services require encrypted transmission"}]},{"tags":[{"name":"list","salience":0.5,"theta":1}],"items":[{"tags":[],"text":"file transfer no loss elastic not time sensitive"},{"tags":[],"text":"email no loss elastic not time sensitive"},{"tags":[],"text":"web http no loss elastic not time sensitive"},{"tags":[],"text":"audio loss tolerant 5kbps 1mbps few ms delay ok"},{"tags":[],"text":"video loss tolerant 10kbps 5mbps few ms delay ok"},{"tags":[],"text":"games loss tolerant 5kbps 5mbps few secs delay ok"},{"tags":[],"text":"texting no loss elastic few ms delay ok"}]},{"tags":[{"name":"list","salience":0.5,"theta":1}],"items":[{"tags":[],"text":"logical communication between processes on different hosts"},{"tags":[],"text":"transport protocols run within end point processes sender splits messages into segments passes to network layer receiver reassembles segments into messages passes to app layer"},{"tags":[],"text":"sender splits messages into segments passes to network layer"},{"tags":[],"text":"receiver reassembles segments into messages passes to app layer"}]},{"tags":[{"name":"list","salience":0.5,"theta":1}],"items":[{"tags":[],"text":"sender splits messages into segments passes to network layer"},{"tags":[],"text":"receiver reassembles segments into messages passes to app layer"}]},{"tags":[{"name":"list","salience":0.5,"theta":1}],"items":[{"tags":[],"text":"tcp reliable connection oriented protocol byte stream"},{"tags":[],"text":"udp unreliable simple connectionless protocol segments"}]},{"tags":[{"name":"list","salience":0.5,"theta":1}],"items":[{"tags":[],"text":"reliable transport data flow between sender receiver"},{"tags":[],"text":"flow control sender doesn t overwhelm receiver"},{"tags":[],"text":"congestion control slow sender if network congested"},{"tags":[],"text":"connection oriented setup required between client server"}]},{"tags":[{"name":"list","salience":0.5,"theta":1}],"items":[{"tags":[],"text":"fast for sender but unreliable data transfer"}]},{"tags":[{"name":"list","salience":0.5,"theta":1}],"items":[{"tags":[],"text":"ip is an unreliable network layer protocol"},{"tags":[],"text":"tcp provides reliable stream of data on top of ip"}]},{"tags":[{"name":"list","salience":0.5,"theta":1}],"items":[{"tags":[],"text":"set up connection between sender and receiver"},{"tags":[],"text":"sender transmits a pipeline of segments"},{"tags":[],"text":"expect ack for each segment"},{"tags":[],"text":"retransmissions triggered by timeouts and duplicate acks"},{"tags":[],"text":"receiver manages receipt and collation of segments"}]},{"tags":[{"name":"list","salience":0.5,"theta":1}],"items":[{"tags":[],"text":"small segment headers no connection setup costs"},{"tags":[],"text":"udp senders can transmit segments as fast as they like"},{"tags":[],"text":"segments are handled independently of each other"}]},{"tags":[{"name":"list","salience":0.5,"theta":1}],"items":[{"tags":[],"text":"sender and receiver treat segment data as sequence of ints"},{"tags":[],"text":"sender compute sum of ints store in header"},{"tags":[],"text":"receiver compute sum of ints compare to checksum"}]},{"tags":[{"name":"list","salience":0.5,"theta":1}],"items":[{"tags":[],"text":"hosts specified by ip addresses e g 129 94 242 19"}]},{"tags":[{"name":"list","salience":0.5,"theta":1}],"items":[{"tags":[],"text":"for outgoing packets select the next hop host pass packet to link layer to transmit to host"},{"tags":[],"text":"select the next hop host"},{"tags":[],"text":"pass packet to link layer to transmit to host"},{"tags":[],"text":"for incoming packets if reached destination extract payload pass to transport layer if not reached destination treat as outgoing packet"},{"tags":[],"text":"if reached destination extract payload pass to transport layer"},{"tags":[],"text":"if not reached destination treat as outgoing packet"},{"tags":[],"text":"for all packets transmissions error detection diagnostics"},{"tags":[],"text":"may also split oversize segments into smaller packets"}]},{"tags":[{"name":"list","salience":0.5,"theta":1}],"items":[{"tags":[],"text":"select the next hop host"},{"tags":[],"text":"pass packet to link layer to transmit to host"}]},{"tags":[{"name":"list","salience":0.5,"theta":1}],"items":[{"tags":[],"text":"if reached destination extract payload pass to transport layer"},{"tags":[],"text":"if not reached destination treat as outgoing packet"}]},{"tags":[{"name":"list","salience":0.5,"theta":1}],"items":[{"tags":[],"text":"host addressing and routing of packets"},{"tags":[],"text":"splitting and reassembly of large packets"}]},{"tags":[{"name":"list","salience":0.5,"theta":1}],"items":[{"tags":[],"text":"each host maintains a routing table maps address next hop"},{"tags":[],"text":"uses subnets to reduce table size all hosts in a subnet have common prefix e g cse 129 94 2xx xxx all ip addresses with common prefix sent to same host gateway"},{"tags":[],"text":"all hosts in a subnet have common prefix e g cse 129 94 2xx xxx"},{"tags":[],"text":"all ip addresses with common prefix sent to same host gateway"},{"tags":[],"text":"routing table maintained dynamically hosts transmit active signals to each other periodically"},{"tags":[],"text":"hosts transmit active signals to each other periodically"}]},{"tags":[{"name":"list","salience":0.5,"theta":1}],"items":[{"tags":[],"text":"all hosts in a subnet have common prefix e g cse 129 94 2xx xxx"},{"tags":[],"text":"all ip addresses with common prefix sent to same host gateway"}]},{"tags":[{"name":"list","salience":0.5,"theta":1}],"items":[{"tags":[],"text":"hosts transmit active signals to each other periodically"}]},{"tags":[{"name":"list","salience":0.5,"theta":1}],"items":[{"tags":[],"text":"every host on network has network layer implementation"},{"tags":[],"text":"implemented as a combination of hardware software"},{"tags":[],"text":"each host contains a network interface card nic"},{"tags":[],"text":"connected to system bus as i o device"}]},{"tags":[{"name":"list","salience":0.5,"theta":1}],"items":[{"tags":[],"text":"flow control pacing between adjacent sending and receiving nodes"},{"tags":[],"text":"error detection detects transmission errors flags error to network layer"},{"tags":[],"text":"error correction can identify and correct single bit errors"}]},{"tags":[{"name":"list","salience":0.5,"theta":1}],"items":[{"tags":[],"text":"ethernet is a cable physically connecting multiple hosts"},{"tags":[],"text":"data broadcast onto cable tagged with receiver mac address"},{"tags":[],"text":"devices recognise their own data using mac address"}]},{"tags":[{"name":"list","salience":0.5,"theta":1}],"items":[{"tags":[],"text":"interference two different packets broadcast at same time"},{"tags":[],"text":"collision node receives two or more signals at same time"}]},{"tags":[{"name":"list","salience":0.5,"theta":1}],"items":[{"tags":[],"text":"channel partitioning partition channel based on time slices frequency bands allocate one partition to each node for exclusive use"},{"tags":[],"text":"partition channel based on time slices frequency bands"},{"tags":[],"text":"allocate one partition to each node for exclusive use"},{"tags":[],"text":"random access allow collisions need mechanisms to recover from collisions"},{"tags":[],"text":"allow collisions need mechanisms to recover from collisions"},{"tags":[],"text":"taking turns nodes take turns nodes with more to send get longer turns"},{"tags":[],"text":"nodes take turns nodes with more to send get longer turns"}]},{"tags":[{"name":"list","salience":0.5,"theta":1}],"items":[{"tags":[],"text":"partition channel based on time slices frequency bands"},{"tags":[],"text":"allocate one partition to each node for exclusive use"}]},{"tags":[{"name":"list","salience":0.5,"theta":1}],"items":[{"tags":[],"text":"allow collisions need mechanisms to recover from collisions"}]},{"tags":[{"name":"list","salience":0.5,"theta":1}],"items":[{"tags":[],"text":"nodes take turns nodes with more to send get longer turns"}]},{"tags":[{"name":"list","salience":0.5,"theta":1}],"items":[{"tags":[],"text":"large number of autonomous sensors"},{"tags":[],"text":"one or multiple base station mobile or static"},{"tags":[],"text":"reasons for popularity low cost ability to solve and interact with real world problems and challenges"},{"tags":[],"text":"low cost"},{"tags":[],"text":"ability to solve and interact with real world problems and challenges"}]},{"tags":[{"name":"list","salience":0.5,"theta":1}],"items":[{"tags":[],"text":"low cost"},{"tags":[],"text":"ability to solve and interact with real world problems and challenges"}]},{"tags":[{"name":"list","salience":0.5,"theta":1}],"items":[{"tags":[],"text":"operate in unattended and hostile environments"},{"tags":[],"text":"potentially interact with sensitive data"}]},{"tags":[{"name":"list","salience":0.5,"theta":1}],"items":[{"tags":[],"text":"environmental habitat monitoring"},{"tags":[],"text":"acoustic detection"},{"tags":[],"text":"seismic detection"},{"tags":[],"text":"military surveillance"},{"tags":[],"text":"inventory tracking"},{"tags":[],"text":"medical monitoring"},{"tags":[],"text":"smart spaces"},{"tags":[],"text":"process monitoring"}]},{"tags":[{"name":"list","salience":0.5,"theta":1}],"items":[{"tags":[],"text":"difficult to apply existing approaches to wsn security"},{"tags":[],"text":"very limited resources limited memory and storage space power limitation"},{"tags":[],"text":"limited memory and storage space"},{"tags":[],"text":"power limitation"},{"tags":[],"text":"unreliable communication unreliable transfer connectionless routing packet loss error handling conflicts packet collision latency multihop routing network congestion node processing"},{"tags":[],"text":"unreliable transfer connectionless routing packet loss error handling"},{"tags":[],"text":"conflicts packet collision"},{"tags":[],"text":"latency multihop routing network congestion node processing"},{"tags":[],"text":"unattended operation exposure to physical attacks bad weather etc managed remotely physical tampering no central management point"},{"tags":[],"text":"exposure to physical attacks bad weather etc"},{"tags":[],"text":"managed remotely physical tampering"},{"tags":[],"text":"no central management point"}]},{"tags":[{"name":"list","salience":0.5,"theta":1}],"items":[{"tags":[],"text":"limited memory and storage space"},{"tags":[],"text":"power limitation"}]},{"tags":[{"name":"list","salience":0.5,"theta":1}],"items":[{"tags":[],"text":"unreliable transfer connectionless routing packet loss error handling"},{"tags":[],"text":"conflicts packet collision"},{"tags":[],"text":"latency multihop routing network congestion node processing"}]},{"tags":[{"name":"list","salience":0.5,"theta":1}],"items":[{"tags":[],"text":"exposure to physical attacks bad weather etc"},{"tags":[],"text":"managed remotely physical tampering"},{"tags":[],"text":"no central management point"}]},{"tags":[{"name":"list","salience":0.5,"theta":1}],"items":[{"tags":[],"text":"data confidentiality military sensitive data encryption"},{"tags":[],"text":"military sensitive data"},{"tags":[],"text":"encryption"},{"tags":[],"text":"data integrity"},{"tags":[],"text":"data freshness important because of shared key strategies"},{"tags":[],"text":"important because of shared key strategies"},{"tags":[],"text":"availability"},{"tags":[],"text":"self organization"},{"tags":[],"text":"authentication"}]},{"tags":[{"name":"list","salience":0.5,"theta":1}],"items":[{"tags":[],"text":"military sensitive data"},{"tags":[],"text":"encryption"}]},{"tags":[{"name":"list","salience":0.5,"theta":1}],"items":[{"tags":[],"text":"important because of shared key strategies"}]},{"tags":[{"name":"list","salience":0.5,"theta":1}],"items":[{"tags":[],"text":"denial of service attack"},{"tags":[],"text":"the sybil attack malicious device taking on multiple identities voting systems"},{"tags":[],"text":"malicious device taking on multiple identities voting systems"},{"tags":[],"text":"traffic analysis attack"},{"tags":[],"text":"node replication attacks"},{"tags":[],"text":"attacks against privacy monitor and eavesdropping traffic analysis camouflage"},{"tags":[],"text":"monitor and eavesdropping traffic analysis camouflage"},{"tags":[],"text":"physical attacks"}]},{"tags":[{"name":"list","salience":0.5,"theta":1}],"items":[{"tags":[],"text":"malicious device taking on multiple identities voting systems"}]},{"tags":[{"name":"list","salience":0.5,"theta":1}],"items":[{"tags":[],"text":"monitor and eavesdropping traffic analysis camouflage"}]},{"tags":[{"name":"list","salience":0.5,"theta":1}],"items":[{"tags":[],"text":"any event that diminishes or eliminates network s capacity to perform its expected function"}]},{"tags":[{"name":"list","salience":0.5,"theta":1}],"items":[{"tags":[],"text":"computational overhead in wsn"},{"tags":[],"text":"critical applications"}]},{"tags":[{"name":"list","salience":0.5,"theta":1}],"items":[{"tags":[],"text":"intermittent jamming"},{"tags":[],"text":"constant jamming"},{"tags":[],"text":"link layer attacks collision"}]},{"tags":[{"name":"list","salience":0.5,"theta":1}],"items":[{"tags":[],"text":"malicious device illegitimately taking on multiple identities"}]},{"tags":[{"name":"list","salience":0.5,"theta":1}],"items":[{"tags":[],"text":"routing algorithms data aggregation voting"},{"tags":[],"text":"fair resource allocation and foiling misbehavior detection"}]},{"tags":[{"name":"list","salience":0.5,"theta":1}],"items":[{"tags":[],"text":"multiple votes registered using multiple identities"}]},{"tags":[{"name":"list","salience":0.5,"theta":1}],"items":[{"tags":[],"text":"add another node to sensor network by replicating node id"}]},{"tags":[{"name":"list","salience":0.5,"theta":1}],"items":[{"tags":[],"text":"packet corruption"},{"tags":[],"text":"incorrect packet routing"}]},{"tags":[{"name":"list","salience":0.5,"theta":1}],"items":[{"tags":[],"text":"to manipulate a specific segment of the network"}]},{"tags":[{"name":"list","salience":0.5,"theta":1}],"items":[{"tags":[],"text":"destruction tampering with circuitry or modification of programming"}]},{"tags":[{"name":"list","salience":0.5,"theta":1}],"items":[{"tags":[],"text":"nodes operate in hostile outdoor environments"},{"tags":[],"text":"small form factor"},{"tags":[],"text":"unattended nature of deployment"}]},{"tags":[{"name":"list","salience":0.5,"theta":1}],"items":[{"tags":[],"text":"modification attack malicious node modifies data in transit between source and destination"},{"tags":[],"text":"malicious node modifies data in transit between source and destination"},{"tags":[],"text":"selective forwarding attack malicious node intends to selectively drop some packets"},{"tags":[],"text":"malicious node intends to selectively drop some packets"},{"tags":[],"text":"black hole attack malicious node intend to refuse routing and drop all packets through"},{"tags":[],"text":"malicious node intend to refuse routing and drop all packets through"}]},{"tags":[{"name":"list","salience":0.5,"theta":1}],"items":[{"tags":[],"text":"malicious node modifies data in transit between source and destination"}]},{"tags":[{"name":"list","salience":0.5,"theta":1}],"items":[{"tags":[],"text":"malicious node intends to selectively drop some packets"}]},{"tags":[{"name":"list","salience":0.5,"theta":1}],"items":[{"tags":[],"text":"malicious node intend to refuse routing and drop all packets through"}]},{"tags":[{"name":"list","salience":0.5,"theta":1}],"items":[{"tags":[],"text":"encryption"},{"tags":[],"text":"multipath routing"},{"tags":[],"text":"overhearing"},{"tags":[],"text":"concealed data aggregation"},{"tags":[],"text":"more"}]}],"block":[{"tags":[{"name":"paragraph","salience":0.5,"theta":1}],"text":"f network architecture"},{"tags":[{"name":"paragraph","salience":0.5,"theta":1}],"text":"networks"},{"tags":[{"name":"paragraph","salience":0.5,"theta":1}],"text":"networks2 52"},{"tags":[{"name":"paragraph","salience":0.5,"theta":1}],"text":"network interconnected collection of computers"},{"tags":[{"name":"paragraph","salience":0.5,"theta":1}],"text":"flavours of networks"},{"tags":[{"name":"paragraph","salience":0.5,"theta":1}],"text":"networks3 52"},{"tags":[{"name":"paragraph","salience":0.5,"theta":1}],"text":"what are the basic requirements for a network"},{"tags":[{"name":"paragraph","salience":0.5,"theta":1}],"text":"overview of network communication4 52"},{"tags":[{"name":"paragraph","salience":0.5,"theta":1}],"text":"how a file is sent over the network"},{"tags":[{"name":"paragraph","salience":0.5,"theta":1}],"text":"the internet5 52"},{"tags":[{"name":"paragraph","salience":0.5,"theta":1}],"text":"components of the internet millions of connected devices e g pc server laptop smartphone host end system running network apps communication links e g fibre copper radio satellite bandwidth transmission rate packet switches e g routers network switches compute next hop forward packets"},{"tags":[{"name":"paragraph","salience":0.5,"theta":1}],"text":"the internet6 52"},{"tags":[{"name":"paragraph","salience":0.5,"theta":1}],"text":"internet communications are based on a 5 layer stack"},{"tags":[{"name":"paragraph","salience":0.5,"theta":1}],"text":"why so many layers of abstraction"},{"tags":[{"name":"paragraph","salience":0.5,"theta":1}],"text":"the internet7 52"},{"tags":[{"name":"paragraph","salience":0.5,"theta":1}],"text":"path of data through network layers"},{"tags":[{"name":"paragraph","salience":0.5,"theta":1}],"text":"protocols8 52"},{"tags":[{"name":"paragraph","salience":0.5,"theta":1}],"text":"network protocols govern all communication activity on the network"},{"tags":[{"name":"paragraph","salience":0.5,"theta":1}],"text":"protocols provide communication rules"},{"tags":[{"name":"paragraph","salience":0.5,"theta":1}],"text":"network application layer9 52"},{"tags":[{"name":"paragraph","salience":0.5,"theta":1}],"text":"the application layer directly supports the apps we interact with e g"},{"tags":[{"name":"paragraph","salience":0.5,"theta":1}],"text":"client server architecture10 52"},{"tags":[{"name":"paragraph","salience":0.5,"theta":1}],"text":"client server common way of structuring network communication"},{"tags":[{"name":"paragraph","salience":0.5,"theta":1}],"text":"server is a data provider"},{"tags":[{"name":"paragraph","salience":0.5,"theta":1}],"text":"addressing11 52"},{"tags":[{"name":"paragraph","salience":0.5,"theta":1}],"text":"server processes must have a unique internet wide address"},{"tags":[{"name":"paragraph","salience":0.5,"theta":1}],"text":"ip addresses12 52"},{"tags":[{"name":"paragraph","salience":0.5,"theta":1}],"text":"ip address unique identifier for host on network"},{"tags":[{"name":"paragraph","salience":0.5,"theta":1}],"text":"application layer protocols13 52"},{"tags":[{"name":"paragraph","salience":0.5,"theta":1}],"text":"each application layer protocol defines"},{"tags":[{"name":"paragraph","salience":0.5,"theta":1}],"text":"the http protocol14 52"},{"tags":[{"name":"paragraph","salience":0.5,"theta":1}],"text":"http hypertext transfer protocol"},{"tags":[{"name":"paragraph","salience":0.5,"theta":1}],"text":"web pages are the primary type of response"},{"tags":[{"name":"paragraph","salience":0.5,"theta":1}],"text":"the http protocol15 52"},{"tags":[{"name":"paragraph","salience":0.5,"theta":1}],"text":"application layer protocol for the web client server model client web browser e g chrome sends http requests receives http responses shows response as web page server web server e g apache receives http requests sends http responses"},{"tags":[{"name":"paragraph","salience":0.5,"theta":1}],"text":"client server model"},{"tags":[{"name":"paragraph","salience":0.5,"theta":1}],"text":"the http protocol16 52"},{"tags":[{"name":"paragraph","salience":0.5,"theta":1}],"text":"transport layer view of http application layer"},{"tags":[{"name":"paragraph","salience":0.5,"theta":1}],"text":"the http protocol17 52"},{"tags":[{"name":"paragraph","salience":0.5,"theta":1}],"text":"http request message ascii text"},{"tags":[{"name":"paragraph","salience":0.5,"theta":1}],"text":"url can also include a query string e g"},{"tags":[{"name":"paragraph","salience":0.5,"theta":1}],"text":"the http protocol18 52"},{"tags":[{"name":"paragraph","salience":0.5,"theta":1}],"text":"first line of http request contains method path protocol e g"},{"tags":[{"name":"paragraph","salience":0.5,"theta":1}],"text":"the http protocol19 52"},{"tags":[{"name":"paragraph","salience":0.5,"theta":1}],"text":"http response message ascii text"},{"tags":[{"name":"paragraph","salience":0.5,"theta":1}],"text":"the http protocol20 52"},{"tags":[{"name":"paragraph","salience":0.5,"theta":1}],"text":"response status codes appear in first line of http response"},{"tags":[{"name":"paragraph","salience":0.5,"theta":1}],"text":"server addresses dns 21 52"},{"tags":[{"name":"paragraph","salience":0.5,"theta":1}],"text":"network requests typically use server names e g"},{"tags":[{"name":"paragraph","salience":0.5,"theta":1}],"text":"domain name system provides name ip address mapping"},{"tags":[{"name":"paragraph","salience":0.5,"theta":1}],"text":"can access this on unix linux via the host command e g"},{"tags":[{"name":"paragraph","salience":0.5,"theta":1}],"text":"assumes that you have a network connection"},{"tags":[{"name":"paragraph","salience":0.5,"theta":1}],"text":"server addresses dns 22 52"},{"tags":[{"name":"paragraph","salience":0.5,"theta":1}],"text":"in real life often have one object referenced by many names e g"},{"tags":[{"name":"paragraph","salience":0.5,"theta":1}],"text":"server addresses dns 23 52"},{"tags":[{"name":"paragraph","salience":0.5,"theta":1}],"text":"domain name system dns"},{"tags":[{"name":"paragraph","salience":0.5,"theta":1}],"text":"why not centralize dns"},{"tags":[{"name":"paragraph","salience":0.5,"theta":1}],"text":"server addresses dns 24 52"},{"tags":[{"name":"paragraph","salience":0.5,"theta":1}],"text":"resolving www amazon com in this system"},{"tags":[{"name":"paragraph","salience":0.5,"theta":1}],"text":"server addresses dns 25 52"},{"tags":[{"name":"paragraph","salience":0.5,"theta":1}],"text":"two styles of name resolution"},{"tags":[{"name":"paragraph","salience":0.5,"theta":1}],"text":"server addresses dns 26 52"},{"tags":[{"name":"paragraph","salience":0.5,"theta":1}],"text":"how are the various dns servers structured managed"},{"tags":[{"name":"paragraph","salience":0.5,"theta":1}],"text":"network architecture27 52"},{"tags":[{"name":"paragraph","salience":0.5,"theta":1}],"text":"five layer model"},{"tags":[{"name":"paragraph","salience":0.5,"theta":1}],"text":"software at each level uses headers appropriate for its purpose"},{"tags":[{"name":"paragraph","salience":0.5,"theta":1}],"text":"transport layer28 52"},{"tags":[{"name":"paragraph","salience":0.5,"theta":1}],"text":"transport layer deals with"},{"tags":[{"name":"paragraph","salience":0.5,"theta":1}],"text":"transport layer29 52"},{"tags":[{"name":"paragraph","salience":0.5,"theta":1}],"text":"properties of some common apps"},{"tags":[{"name":"paragraph","salience":0.5,"theta":1}],"text":"transport layer protocols30 52"},{"tags":[{"name":"paragraph","salience":0.5,"theta":1}],"text":"transport layer protocols provide"},{"tags":[{"name":"paragraph","salience":0.5,"theta":1}],"text":"transport layer protocols31 52"},{"tags":[{"name":"paragraph","salience":0.5,"theta":1}],"text":"tcp transmission control protocol provides"},{"tags":[{"name":"paragraph","salience":0.5,"theta":1}],"text":"udp user datagram protocol provides"},{"tags":[{"name":"paragraph","salience":0.5,"theta":1}],"text":"transport layer protocols32 52"},{"tags":[{"name":"paragraph","salience":0.5,"theta":1}],"text":"tcp is typically layered on top of ip protocol"},{"tags":[{"name":"paragraph","salience":0.5,"theta":1}],"text":"transport layer protocols33 52"},{"tags":[{"name":"paragraph","salience":0.5,"theta":1}],"text":"above comments makes udp sound sub standard"},{"tags":[{"name":"paragraph","salience":0.5,"theta":1}],"text":"however it has a number of advantages over tcp"},{"tags":[{"name":"paragraph","salience":0.5,"theta":1}],"text":"error detection requires use of checksum"},{"tags":[{"name":"paragraph","salience":0.5,"theta":1}],"text":"network layer34 52"},{"tags":[{"name":"paragraph","salience":0.5,"theta":1}],"text":"transport layer provides a way for app processes to communicate"},{"tags":[{"name":"paragraph","salience":0.5,"theta":1}],"text":"network layer provides communication between hosts"},{"tags":[{"name":"paragraph","salience":0.5,"theta":1}],"text":"network layer protocol35 52"},{"tags":[{"name":"paragraph","salience":0.5,"theta":1}],"text":"ip internet protocol is a network layer protocol that provides"},{"tags":[{"name":"paragraph","salience":0.5,"theta":1}],"text":"network layer protocol36 52"},{"tags":[{"name":"paragraph","salience":0.5,"theta":1}],"text":"simplified routing algorithm ip forwarding"},{"tags":[{"name":"paragraph","salience":0.5,"theta":1}],"text":"link layer37 52"},{"tags":[{"name":"paragraph","salience":0.5,"theta":1}],"text":"link layer takes packets from network layer and transmits them"},{"tags":[{"name":"paragraph","salience":0.5,"theta":1}],"text":"ethernet38 52"},{"tags":[{"name":"paragraph","salience":0.5,"theta":1}],"text":"ethernet is an example of link layer implementation"},{"tags":[{"name":"paragraph","salience":0.5,"theta":1}],"text":"mac address media access control address stored in nic"},{"tags":[{"name":"paragraph","salience":0.5,"theta":1}],"text":"ethernet39 52"},{"tags":[{"name":"paragraph","salience":0.5,"theta":1}],"text":"ethernet is a shared broadcast medium and so"},{"tags":[{"name":"paragraph","salience":0.5,"theta":1}],"text":"example multiple access protocols"},{"tags":[{"name":"paragraph","salience":0.5,"theta":1}],"text":"ethernet40 52"},{"tags":[{"name":"paragraph","salience":0.5,"theta":1}],"text":"a random access transmission protocol csma"},{"tags":[{"name":"paragraph","salience":0.5,"theta":1}],"text":"wireless sensor network security41 52"},{"tags":[{"name":"paragraph","salience":0.5,"theta":1}],"text":"what is wsn"},{"tags":[{"name":"paragraph","salience":0.5,"theta":1}],"text":"a wireless sensor network wsn is a wireless network consisting of spatially distributed autonomous devices using sensors to cooperatively monitor physical or environmental conditions such as temperature sound vibration pressure motion or pollutants at different locations"},{"tags":[{"name":"paragraph","salience":0.5,"theta":1}],"text":"wireless sensor network security42 52"},{"tags":[{"name":"paragraph","salience":0.5,"theta":1}],"text":"security of wireless sensor networks"},{"tags":[{"name":"paragraph","salience":0.5,"theta":1}],"text":"wsns operate under resource constraints"},{"tags":[{"name":"paragraph","salience":0.5,"theta":1}],"text":"applications"},{"tags":[{"name":"paragraph","salience":0.5,"theta":1}],"text":"wireless sensor network security43 52"},{"tags":[{"name":"paragraph","salience":0.5,"theta":1}],"text":"main aspects to discuss"},{"tags":[{"name":"paragraph","salience":0.5,"theta":1}],"text":"wireless sensor network security44 52"},{"tags":[{"name":"paragraph","salience":0.5,"theta":1}],"text":"obstacles to sensor network security"},{"tags":[{"name":"paragraph","salience":0.5,"theta":1}],"text":"wireless sensor network security45 52"},{"tags":[{"name":"paragraph","salience":0.5,"theta":1}],"text":"security requirements of a wireless sensor network"},{"tags":[{"name":"paragraph","salience":0.5,"theta":1}],"text":"wsn attacks46 52"},{"tags":[{"name":"paragraph","salience":0.5,"theta":1}],"text":"types of attacks"},{"tags":[{"name":"paragraph","salience":0.5,"theta":1}],"text":"wsn attacks47 52"},{"tags":[{"name":"paragraph","salience":0.5,"theta":1}],"text":"denial of service dos attack"},{"tags":[{"name":"paragraph","salience":0.5,"theta":1}],"text":"constraints"},{"tags":[{"name":"paragraph","salience":0.5,"theta":1}],"text":"wsn attacks48 52"},{"tags":[{"name":"paragraph","salience":0.5,"theta":1}],"text":"sybil attack"},{"tags":[{"name":"paragraph","salience":0.5,"theta":1}],"text":"wsn attacks49 52"},{"tags":[{"name":"paragraph","salience":0.5,"theta":1}],"text":"node replication attacks"},{"tags":[{"name":"paragraph","salience":0.5,"theta":1}],"text":"wsn attacks50 52"},{"tags":[{"name":"paragraph","salience":0.5,"theta":1}],"text":"physical attacks"},{"tags":[{"name":"paragraph","salience":0.5,"theta":1}],"text":"wsn attacks51 52"},{"tags":[{"name":"paragraph","salience":0.5,"theta":1}],"text":"other kinds of attack"},{"tags":[{"name":"paragraph","salience":0.5,"theta":1}],"text":"wsn attacks52 52"},{"tags":[{"name":"paragraph","salience":0.5,"theta":1}],"text":"defense strategies"},{"tags":[{"name":"paragraph","salience":0.5,"theta":1}],"text":"produced 2 may 2018"}]}